{
  "last_updated": "2026-05-15 14:38:27",
  "results": [
    {
      "symbol": "XAUUSD",
      "name": "ゴールド",
      "category": "metals",
      "bid": 4566.27,
      "ask": 4566.49,
      "spread": 0.22,
      "spread_pct": 0.004818,
      "success": true,
      "error": null,
      "timestamp": 1778823521.7616599,
      "earnings_date": null,
      "stale": false
    },
    {
      "symbol": "XAGUSD",
      "name": "シルバー",
      "category": "metals",
      "bid": 78.165,
      "ask": 78.268,
      "spread": 0.103,
      "spread_pct": 0.131686,
      "success": true,
      "error": null,
      "timestamp": 1778823521.3128824,
      "earnings_date": null,
      "stale": false
    },
    {
      "symbol": "XPTUSD",
      "name": "プラチナ",
      "category": "metals",
      "bid": 1996.28,
      "ask": 2006.44,
      "spread": 10.16,
      "spread_pct": 0.507655,
      "success": true,
      "error": null,
      "timestamp": 1778823521.6335301,
      "earnings_date": null,
      "stale": false
    },
    {
      "symbol": "XPDUSD",
      "name": "パラジウム",
      "category": "metals",
      "bid": 1415.36,
      "ask": 1422.56,
      "spread": 7.2,
      "spread_pct": 0.507414,
      "success": true,
      "error": null,
      "timestamp": 1778823519.5126882,
      "earnings_date": null,
      "stale": false
    },
    {
      "symbol": "XALUSD",
      "name": "アルミニウム",
      "category": "metals",
      "bid": 3598.04,
      "ask": 3613.46,
      "spread": 15.42,
      "spread_pct": 0.42765,
      "success": true,
      "error": null,
      "timestamp": 1778823517.5588756,
      "earnings_date": null,
      "stale": false
    },
    {
      "symbol": "COPPER",
      "name": "銅",
      "category": "metals",
      "bid": 658.63,
      "ask": 659.03,
      "spread": 0.4,
      "spread_pct": 0.060714,
      "success": true,
      "error": null,
      "timestamp": 1778745929.310647,
      "earnings_date": null,
      "stale": true
    },
    {
      "symbol": "USOIL",
      "name": "原油(WTI)",
      "category": "commodities",
      "bid": 98.564,
      "ask": 98.6,
      "spread": 0.036,
      "spread_pct": 0.036518,
      "success": true,
      "error": null,
      "timestamp": 1778823521.6671176,
      "earnings_date": null,
      "stale": false
    },
    {
      "symbol": "UKOIL",
      "name": "原油(ブレント)",
      "category": "commodities",
      "bid": 107.298,
      "ask": 107.33,
      "spread": 0.032,
      "spread_pct": 0.029819,
      "success": true,
      "error": null,
      "timestamp": 1778823521.635107,
      "earnings_date": null,
      "stale": false
    },
    {
      "symbol": "NGAS",
      "name": "天然ガス",
      "category": "commodities",
      "bid": 2.915,
      "ask": 2.928,
      "spread": 0.013,
      "spread_pct": 0.444977,
      "success": true,
      "error": null,
      "timestamp": 1778823504.0632682,
      "earnings_date": null,
      "stale": false
    },
    {
      "symbol": "SP500",
      "name": "S&P 500",
      "category": "indices",
      "bid": 7477.79,
      "ask": 7478.15,
      "spread": 0.36,
      "spread_pct": 0.004814,
      "success": true,
      "error": null,
      "timestamp": 1778823520.240245,
      "earnings_date": null,
      "stale": false
    },
    {
      "symbol": "TECH100",
      "name": "NASDAQ 100",
      "category": "indices",
      "bid": 29383.84,
      "ask": 29384.26,
      "spread": 0.42,
      "spread_pct": 0.001429,
      "success": true,
      "error": null,
      "timestamp": 1778823521.226271,
      "earnings_date": null,
      "stale": false
    },
    {
      "symbol": "DJ30",
      "name": "ダウ工業30",
      "category": "indices",
      "bid": 49983.3,
      "ask": 49984.51,
      "spread": 1.21,
      "spread_pct": 0.002421,
      "success": true,
      "error": null,
      "timestamp": 1778823521.3136613,
      "earnings_date": null,
      "stale": false
    },
    {
      "symbol": "GER30",
      "name": "ドイツDAX",
      "category": "indices",
      "bid": 24151.31,
      "ask": 24152.49,
      "spread": 1.18,
      "spread_pct": 0.004886,
      "success": true,
      "error": null,
      "timestamp": 1778823520.8866084,
      "earnings_date": null,
      "stale": false
    },
    {
      "symbol": "JPN225",
      "name": "日経225",
      "category": "indices",
      "bid": 61390.15,
      "ask": 61398.85,
      "spread": 8.7,
      "spread_pct": 0.014171,
      "success": true,
      "error": null,
      "timestamp": 1778823521.374693,
      "earnings_date": null,
      "stale": false
    },
    {
      "symbol": "UK100",
      "name": "FTSE 100",
      "category": "indices",
      "bid": 10286.47,
      "ask": 10287.19,
      "spread": 0.72,
      "spread_pct": 0.006999,
      "success": true,
      "error": null,
      "timestamp": 1778823522.1273172,
      "earnings_date": null,
      "stale": false
    },
    {
      "symbol": "GBPUSD",
      "name": "ポンド/ドル",
      "category": "forex",
      "bid": 1.3353,
      "ask": 1.3354,
      "spread": 0.0001,
      "spread_pct": 0.007489,
      "success": true,
      "error": null,
      "timestamp": 1778823522.1862314,
      "earnings_date": null,
      "stale": false
    },
    {
      "symbol": "EURUSD",
      "name": "ユーロ/ドル",
      "category": "forex",
      "bid": 1.16455,
      "ask": 1.16466,
      "spread": 0.00011,
      "spread_pct": 0.009445,
      "success": true,
      "error": null,
      "timestamp": 1778823521.7617648,
      "earnings_date": null,
      "stale": false
    },
    {
      "symbol": "AUDUSD",
      "name": "豪ドル/ドル",
      "category": "forex",
      "bid": 0.71698,
      "ask": 0.71707,
      "spread": 9e-05,
      "spread_pct": 0.012552,
      "success": true,
      "error": null,
      "timestamp": 1778823522.3870165,
      "earnings_date": null,
      "stale": false
    },
    {
      "symbol": "NZDUSD",
      "name": "NZドル/ドル",
      "category": "forex",
      "bid": 0.58688,
      "ask": 0.58697,
      "spread": 9e-05,
      "spread_pct": 0.015334,
      "success": true,
      "error": null,
      "timestamp": 1778823521.266866,
      "earnings_date": null,
      "stale": false
    },
    {
      "symbol": "AAPL",
      "name": "Apple",
      "category": "stocks",
      "bid": 299.77,
      "ask": 300.07,
      "spread": 0.3,
      "spread_pct": 0.100027,
      "success": true,
      "error": null,
      "timestamp": 1778823522.322317,
      "earnings_date": "2026-07-30",
      "stale": false
    },
    {
      "symbol": "AMD",
      "name": "AMD",
      "category": "stocks",
      "bid": 434.71,
      "ask": 435.14,
      "spread": 0.43,
      "spread_pct": 0.098868,
      "success": true,
      "error": null,
      "timestamp": 1778823522.1692982,
      "earnings_date": "2026-08-04",
      "stale": false
    },
    {
      "symbol": "AMZN",
      "name": "Amazon",
      "category": "stocks",
      "bid": 265.97,
      "ask": 266.24,
      "spread": 0.27,
      "spread_pct": 0.101464,
      "success": true,
      "error": null,
      "timestamp": 1778823522.332591,
      "earnings_date": "2026-07-30",
      "stale": false
    },
    {
      "symbol": "COST",
      "name": "Costco",
      "category": "stocks",
      "bid": 1044.42,
      "ask": 1050.0,
      "spread": 5.58,
      "spread_pct": 0.532844,
      "success": true,
      "error": null,
      "timestamp": 1778823522.3326788,
      "earnings_date": "2026-05-28",
      "stale": false
    },
    {
      "symbol": "GOOG",
      "name": "Alphabet",
      "category": "stocks",
      "bid": 399.93,
      "ask": 400.37,
      "spread": 0.44,
      "spread_pct": 0.109959,
      "success": true,
      "error": null,
      "timestamp": 1778784739.2200098,
      "earnings_date": "2026-07-23",
      "stale": true
    },
    {
      "symbol": "INTEL",
      "name": "Intel",
      "category": "stocks",
      "bid": 116.42,
      "ask": 116.52,
      "spread": 0.1,
      "spread_pct": 0.085859,
      "success": true,
      "error": null,
      "timestamp": 1778784741.5946746,
      "earnings_date": "2026-07-23",
      "stale": true
    },
    {
      "symbol": "META",
      "name": "Meta",
      "category": "stocks",
      "bid": 611.52,
      "ask": 612.13,
      "spread": 0.61,
      "spread_pct": 0.099702,
      "success": true,
      "error": null,
      "timestamp": 1778823522.2134666,
      "earnings_date": "2026-07-29",
      "stale": false
    },
    {
      "symbol": "MSFT",
      "name": "Microsoft",
      "category": "stocks",
      "bid": 406.88,
      "ask": 407.29,
      "spread": 0.41,
      "spread_pct": 0.100716,
      "success": true,
      "error": null,
      "timestamp": 1778823522.215082,
      "earnings_date": "2026-07-29",
      "stale": false
    },
    {
      "symbol": "MSTR",
      "name": "MicroStrategy",
      "category": "stocks",
      "bid": 181.56,
      "ask": 181.74,
      "spread": 0.18,
      "spread_pct": 0.099092,
      "success": true,
      "error": null,
      "timestamp": 1778823522.248404,
      "earnings_date": "2026-07-30",
      "stale": false
    },
    {
      "symbol": "NFLX",
      "name": "Netflix",
      "category": "stocks",
      "bid": 86.84,
      "ask": 86.97,
      "spread": 0.13,
      "spread_pct": 0.149589,
      "success": true,
      "error": null,
      "timestamp": 1778823522.2888758,
      "earnings_date": "2026-07-16",
      "stale": false
    },
    {
      "symbol": "NVIDIA",
      "name": "NVIDIA",
      "category": "stocks",
      "bid": 235.8,
      "ask": 236.12,
      "spread": 0.32,
      "spread_pct": 0.135616,
      "success": true,
      "error": null,
      "timestamp": 1778784740.8841429,
      "earnings_date": "2026-05-20",
      "stale": true
    },
    {
      "symbol": "ORCL",
      "name": "Oracle",
      "category": "stocks",
      "bid": 191.46,
      "ask": 191.88,
      "spread": 0.42,
      "spread_pct": 0.219127,
      "success": true,
      "error": null,
      "timestamp": 1778823522.3317535,
      "earnings_date": "2026-06-10",
      "stale": false
    },
    {
      "symbol": "PLTR",
      "name": "Palantir",
      "category": "stocks",
      "bid": 131.11,
      "ask": 131.24,
      "spread": 0.13,
      "spread_pct": 0.099104,
      "success": true,
      "error": null,
      "timestamp": 1778823522.0982282,
      "earnings_date": "2026-08-03",
      "stale": false
    },
    {
      "symbol": "TSLA",
      "name": "Tesla",
      "category": "stocks",
      "bid": 433.22,
      "ask": 433.74,
      "spread": 0.52,
      "spread_pct": 0.119959,
      "success": true,
      "error": null,
      "timestamp": 1778823522.3058848,
      "earnings_date": "2026-07-22",
      "stale": false
    },
    {
      "symbol": "TSM",
      "name": "TSMC",
      "category": "stocks",
      "bid": 405.76,
      "ask": 406.17,
      "spread": 0.41,
      "spread_pct": 0.100994,
      "success": true,
      "error": null,
      "timestamp": 1778823522.1712391,
      "earnings_date": "2026-07-16",
      "stale": false
    }
  ]
}